atx_mainframe_bre_analyzer/__init__.py
atx_mainframe_bre_analyzer/server.py
atx_mainframe_bre_analyzer-0.2.5.dist-info/licenses/LICENSE
atx_mainframe_bre_analyzer-0.2.5.dist-info/METADATA
atx_mainframe_bre_analyzer-0.2.5.dist-info/WHEEL
atx_mainframe_bre_analyzer-0.2.5.dist-info/entry_points.txt
atx_mainframe_bre_analyzer-0.2.5.dist-info/top_level.txt
atx_mainframe_bre_analyzer-0.2.5.dist-info/RECORD
