Metadata-Version: 2.4
Name: atx-mainframe-bre-analyzer
Version: 0.2.5
Summary: MCP server for analyzing ATX Business Rules Extraction (BRE) output and mainframe modernization planning
Author-email: Arunkumar Selvam <aruninfy123@gmail.com>
License: MIT
Project-URL: Homepage, https://github.com/arunkumars-mf/atx-mainframe-bre-analyzer
Project-URL: Bug Reports, https://github.com/arunkumars-mf/atx-mainframe-bre-analyzer/issues
Project-URL: Source, https://github.com/arunkumars-mf/atx-mainframe-bre-analyzer
Keywords: mainframe,bre,business-rules-extraction,mcp,atx,modernization,analysis
Classifier: Development Status :: 3 - Alpha
Classifier: Intended Audience :: Developers
Classifier: Topic :: Software Development :: Libraries :: Python Modules
Classifier: Topic :: System :: Systems Administration
Classifier: Programming Language :: Python :: 3
Classifier: Programming Language :: Python :: 3.8
Classifier: Programming Language :: Python :: 3.9
Classifier: Programming Language :: Python :: 3.10
Classifier: Programming Language :: Python :: 3.11
Classifier: Programming Language :: Python :: 3.12
Classifier: License :: OSI Approved :: MIT License
Classifier: Operating System :: OS Independent
Requires-Python: >=3.8
License-File: LICENSE
Requires-Dist: mcp>=1.0.0
Requires-Dist: pydantic>=2.0.0
Dynamic: license-file
